flaskull/__init__.py
flaskull-0.0.1.dist-info/LICENSE
flaskull-0.0.1.dist-info/METADATA
flaskull-0.0.1.dist-info/WHEEL
flaskull-0.0.1.dist-info/top_level.txt
flaskull-0.0.1.dist-info/RECORD
